README.md
setup.cfg
setup.py
live_premailer.egg-info/PKG-INFO
live_premailer.egg-info/SOURCES.txt
live_premailer.egg-info/dependency_links.txt
live_premailer.egg-info/entry_points.txt
live_premailer.egg-info/requires.txt
live_premailer.egg-info/top_level.txt
lpremailer/__init__.py
lpremailer/exceptions.py
lpremailer/main.py
lpremailer/utils.py