Metadata-Version: 1.1
Name: live-premailer
Version: 0.4.1
Summary: Live premailer for jinja2 templates
Home-page: https://github.com/turkus/live-premailer
Author: turkus
Author-email: wojciechrola@wp.pl
License: UNKNOWN
Download-URL: https://github.com/turkus/live-premailer/tarball/0.4.1
Keywords: live,browsersync,jinja2,premailer
Platform: UNKNOWN
Classifier: Programming Language :: Python :: 2.7
Classifier: Programming Language :: Python :: 3.3
Classifier: Programming Language :: Python :: 3.4
Classifier: Programming Language :: Python :: 3.5
Classifier: Programming Language :: Python :: 3.6
Classifier: Programming Language :: Python :: 3.7
